{
  "generatedAt": "deterministic",
  "runs": 3,
  "targetOpenClaw": {
    "status": "ok",
    "configuredPath": "./openclaw",
    "compatRecords": 60,
    "hookNames": 35,
    "apiRegistrars": 49,
    "capturedRegistrars": 26,
    "sdkExports": 296,
    "manifestFields": 40,
    "manifestContractFields": 17
  },
  "fixtureInventory": {
    "fixtures": 57,
    "sourceFiles": 1598,
    "observedHooks": 93,
    "observedRegistrations": 188,
    "observedSdkImports": 1012,
    "contractProbes": 322,
    "issueFindings": 328
  },
  "platform": {
    "os": "linux",
    "arch": "x64",
    "node": "v22.22.2",
    "rssSampler": "ps-immediate-25ms",
    "cpuSampler": "ps-percent-immediate-25ms"
  },
  "summary": {
    "commandCount": 9,
    "sampleCount": 27,
    "rssSampleCount": 1819,
    "cpuSampleCount": 1819,
    "wallTimeBasis": "command-median-p95",
    "p50WallMs": 2117,
    "p95WallMs": 2201,
    "maxPeakRssMb": 439.4,
    "maxRssDeltaMb": 410.6,
    "maxCpuMsEstimate": 2433,
    "maxHarnessHeapDeltaMb": 7.3
  },
  "groups": [
    {
      "category": "baseline",
      "commandCount": 1,
      "p50WallMs": 38,
      "p95WallMs": 40,
      "maxPeakRssMb": 32.5,
      "maxCpuMsEstimate": 0,
      "rssSampleCount": 3,
      "cpuSampleCount": 3,
      "commands": [
        "node-boot"
      ]
    },
    {
      "category": "fixture-scan",
      "commandCount": 1,
      "p50WallMs": 2040,
      "p95WallMs": 2041,
      "maxPeakRssMb": 429.7,
      "maxCpuMsEstimate": 2280,
      "rssSampleCount": 241,
      "cpuSampleCount": 241,
      "commands": [
        "fixture-inspection"
      ]
    },
    {
      "category": "target-registry",
      "commandCount": 1,
      "p50WallMs": 2114,
      "p95WallMs": 2116,
      "maxPeakRssMb": 431.1,
      "maxCpuMsEstimate": 2321,
      "rssSampleCount": 251,
      "cpuSampleCount": 251,
      "commands": [
        "compat-report-registry"
      ]
    },
    {
      "category": "contract-capture",
      "commandCount": 1,
      "p50WallMs": 2137,
      "p95WallMs": 2228,
      "maxPeakRssMb": 431.3,
      "maxCpuMsEstimate": 2433,
      "rssSampleCount": 257,
      "cpuSampleCount": 257,
      "commands": [
        "contract-capture"
      ]
    },
    {
      "category": "synthetic-probes",
      "commandCount": 1,
      "p50WallMs": 2117,
      "p95WallMs": 2153,
      "maxPeakRssMb": 431.7,
      "maxCpuMsEstimate": 2340,
      "rssSampleCount": 249,
      "cpuSampleCount": 249,
      "commands": [
        "synthetic-probe-plan"
      ]
    },
    {
      "category": "cold-import",
      "commandCount": 1,
      "p50WallMs": 2118,
      "p95WallMs": 2133,
      "maxPeakRssMb": 437.5,
      "maxCpuMsEstimate": 2393,
      "rssSampleCount": 253,
      "cpuSampleCount": 253,
      "commands": [
        "cold-import-readiness"
      ]
    },
    {
      "category": "workspace-plan",
      "commandCount": 1,
      "p50WallMs": 2164,
      "p95WallMs": 2179,
      "maxPeakRssMb": 439.4,
      "maxCpuMsEstimate": 2388,
      "rssSampleCount": 258,
      "cpuSampleCount": 258,
      "commands": [
        "workspace-plan"
      ]
    },
    {
      "category": "platform-probes",
      "commandCount": 1,
      "p50WallMs": 2201,
      "p95WallMs": 2219,
      "maxPeakRssMb": 438,
      "maxCpuMsEstimate": 2399,
      "rssSampleCount": 262,
      "cpuSampleCount": 262,
      "commands": [
        "platform-probes"
      ]
    },
    {
      "category": "import-loop",
      "commandCount": 1,
      "p50WallMs": 376,
      "p95WallMs": 380,
      "maxPeakRssMb": 60.5,
      "maxCpuMsEstimate": 180,
      "rssSampleCount": 45,
      "cpuSampleCount": 45,
      "commands": [
        "import-loop-profile"
      ]
    }
  ],
  "commands": [
    {
      "id": "node-boot",
      "label": "Node boot",
      "category": "baseline",
      "command": "/opt/hostedtoolcache/node/22.22.2/x64/bin/node -e 0",
      "samples": [
        {
          "wallMs": 38,
          "peakRssMb": 32.5,
          "rssDeltaMb": 0,
          "peakCpuPercent": 0,
          "cpuMsEstimate": 0,
          "harnessHeapDeltaMb": 0.4,
          "statSampleCount": 1,
          "rssSampleCount": 1,
          "cpuSampleCount": 1,
          "exitCode": 0,
          "stdoutPreview": "",
          "stderrPreview": ""
        },
        {
          "wallMs": 38,
          "peakRssMb": 31.1,
          "rssDeltaMb": 0,
          "peakCpuPercent": 0,
          "cpuMsEstimate": 0,
          "harnessHeapDeltaMb": 0.3,
          "statSampleCount": 1,
          "rssSampleCount": 1,
          "cpuSampleCount": 1,
          "exitCode": 0,
          "stdoutPreview": "",
          "stderrPreview": ""
        },
        {
          "wallMs": 40,
          "peakRssMb": 30,
          "rssDeltaMb": 0,
          "peakCpuPercent": 0,
          "cpuMsEstimate": 0,
          "harnessHeapDeltaMb": 0.2,
          "statSampleCount": 1,
          "rssSampleCount": 1,
          "cpuSampleCount": 1,
          "exitCode": 0,
          "stdoutPreview": "",
          "stderrPreview": ""
        }
      ],
      "wallMs": {
        "min": 38,
        "median": 38,
        "max": 40
      },
      "peakRssMb": {
        "min": 30,
        "median": 31.1,
        "max": 32.5
      },
      "rssDeltaMb": {
        "min": 0,
        "median": 0,
        "max": 0
      },
      "peakCpuPercent": {
        "min": 0,
        "median": 0,
        "max": 0
      },
      "cpuMsEstimate": {
        "min": 0,
        "median": 0,
        "max": 0
      },
      "harnessHeapDeltaMb": {
        "min": 0.2,
        "median": 0.3,
        "max": 0.4
      },
      "statSampleCount": 3,
      "rssSampleCount": 3,
      "cpuSampleCount": 3,
      "exitCodes": [
        0
      ]
    },
    {
      "id": "fixture-inspection",
      "label": "Fixture inspection",
      "category": "fixture-scan",
      "command": "/opt/hostedtoolcache/node/22.22.2/x64/bin/node scripts/inspect-fixtures.mjs --check",
      "samples": [
        {
          "wallMs": 2041,
          "peakRssMb": 429.7,
          "rssDeltaMb": 399.1,
          "peakCpuPercent": 130,
          "cpuMsEstimate": 2280,
          "harnessHeapDeltaMb": -5.1,
          "statSampleCount": 81,
          "rssSampleCount": 81,
          "cpuSampleCount": 81,
          "exitCode": 0,
          "stdoutPreview": "│ 56      │ 'inworld-tts'            │ 'ok'   │ ''                                                                                                                                                                                                                                                                                                                                                                                                                                                                                                                                                                                                          │ 'definePluginEntry,registerSpeechProvider'                                                                                                                                                                                                                                                                                                                                                                                                                                                                                                                                                                                                                                                                                                                                                                                                                                                                                                                                                                                                                                                                                                                                                                                                                                          │ 'speechProviders'                                                                                                                                                                                                                                                                                                                                                                        │\n└─────────┴──────────────────────────┴────────┴─────────────────────────────────────────────────────────────────────────────────────────────────────────────────────────────────────────────────────────────────────────────────────────────────────────────────────────────────────────────────────────────────────────────────────────────────────────────────────────────────────────────────────────────────────────────────────────────────────────────────────────────────────────────────────────────────────────────────────────────────────────────────────────────────────────────────────────────────────────────────────────────────────────────┴─────────────────────────────────────────────────────────────────────────────────────────────────────────────────────────────────────────────────────────────────────────────────────────────────────────────────────────────────────────────────────────────────────────────────────────────────────────────────────────────────────────────────────────────────────────────────────────────────────────────────────────────────────────────────────────────────────────────────────────────────────────────────────────────────────────────────────────────────────────────────────────────────────────────────────────────────────────────────────────────────────────────────────────────────────────────────────────────────────────────────────────────────────────────────────────────────────────────────────────────────────────────────────────────────────────────────────────────────────────────────────────────────────────────────────────────────────────────────────────────────────────────────────────────────────────────────────────────────────────────────────────────────────────────────────────────────────────────────────────────────────────────────────────────────────────────────────────────────────────────────────────────────────────────────────┴──────────────────────────────────────────────────────────────────────────────────────────────────────────────────────────────────────────────────────────────────────────────────────────────────────────────────────────────────────────────────────────────────────────────────────────────────────────────────────────────────────────────────────────────────────────────────────────┘",
          "stderrPreview": ""
        },
        {
          "wallMs": 2040,
          "peakRssMb": 429.5,
          "rssDeltaMb": 397.8,
          "peakCpuPercent": 125,
          "cpuMsEstimate": 2236,
          "harnessHeapDeltaMb": 7.3,
          "statSampleCount": 81,
          "rssSampleCount": 81,
          "cpuSampleCount": 81,
          "exitCode": 0,
          "stdoutPreview": "│ 56      │ 'inworld-tts'            │ 'ok'   │ ''                                                                                                                                                                                                                                                                                                                                                                                                                                                                                                                                                                                                          │ 'definePluginEntry,registerSpeechProvider'                                                                                                                                                                                                                                                                                                                                                                                                                                                                                                                                                                                                                                                                                                                                                                                                                                                                                                                                                                                                                                                                                                                                                                                                                                          │ 'speechProviders'                                                                                                                                                                                                                                                                                                                                                                        │\n└─────────┴──────────────────────────┴────────┴─────────────────────────────────────────────────────────────────────────────────────────────────────────────────────────────────────────────────────────────────────────────────────────────────────────────────────────────────────────────────────────────────────────────────────────────────────────────────────────────────────────────────────────────────────────────────────────────────────────────────────────────────────────────────────────────────────────────────────────────────────────────────────────────────────────────────────────────────────────────────────────────────────────────┴─────────────────────────────────────────────────────────────────────────────────────────────────────────────────────────────────────────────────────────────────────────────────────────────────────────────────────────────────────────────────────────────────────────────────────────────────────────────────────────────────────────────────────────────────────────────────────────────────────────────────────────────────────────────────────────────────────────────────────────────────────────────────────────────────────────────────────────────────────────────────────────────────────────────────────────────────────────────────────────────────────────────────────────────────────────────────────────────────────────────────────────────────────────────────────────────────────────────────────────────────────────────────────────────────────────────────────────────────────────────────────────────────────────────────────────────────────────────────────────────────────────────────────────────────────────────────────────────────────────────────────────────────────────────────────────────────────────────────────────────────────────────────────────────────────────────────────────────────────────────────────────────────────────────────────┴──────────────────────────────────────────────────────────────────────────────────────────────────────────────────────────────────────────────────────────────────────────────────────────────────────────────────────────────────────────────────────────────────────────────────────────────────────────────────────────────────────────────────────────────────────────────────────────┘",
          "stderrPreview": ""
        },
        {
          "wallMs": 2011,
          "peakRssMb": 429.4,
          "rssDeltaMb": 397.9,
          "peakCpuPercent": 138,
          "cpuMsEstimate": 2242,
          "harnessHeapDeltaMb": -5.6,
          "statSampleCount": 79,
          "rssSampleCount": 79,
          "cpuSampleCount": 79,
          "exitCode": 0,
          "stdoutPreview": "│ 56      │ 'inworld-tts'            │ 'ok'   │ ''                                                                                                                                                                                                                                                                                                                                                                                                                                                                                                                                                                                                          │ 'definePluginEntry,registerSpeechProvider'                                                                                                                                                                                                                                                                                                                                                                                                                                                                                                                                                                                                                                                                                                                                                                                                                                                                                                                                                                                                                                                                                                                                                                                                                                          │ 'speechProviders'                                                                                                                                                                                                                                                                                                                                                                        │\n└─────────┴──────────────────────────┴────────┴─────────────────────────────────────────────────────────────────────────────────────────────────────────────────────────────────────────────────────────────────────────────────────────────────────────────────────────────────────────────────────────────────────────────────────────────────────────────────────────────────────────────────────────────────────────────────────────────────────────────────────────────────────────────────────────────────────────────────────────────────────────────────────────────────────────────────────────────────────────────────────────────────────────────┴─────────────────────────────────────────────────────────────────────────────────────────────────────────────────────────────────────────────────────────────────────────────────────────────────────────────────────────────────────────────────────────────────────────────────────────────────────────────────────────────────────────────────────────────────────────────────────────────────────────────────────────────────────────────────────────────────────────────────────────────────────────────────────────────────────────────────────────────────────────────────────────────────────────────────────────────────────────────────────────────────────────────────────────────────────────────────────────────────────────────────────────────────────────────────────────────────────────────────────────────────────────────────────────────────────────────────────────────────────────────────────────────────────────────────────────────────────────────────────────────────────────────────────────────────────────────────────────────────────────────────────────────────────────────────────────────────────────────────────────────────────────────────────────────────────────────────────────────────────────────────────────────────────────────────────┴──────────────────────────────────────────────────────────────────────────────────────────────────────────────────────────────────────────────────────────────────────────────────────────────────────────────────────────────────────────────────────────────────────────────────────────────────────────────────────────────────────────────────────────────────────────────────────────┘",
          "stderrPreview": ""
        }
      ],
      "wallMs": {
        "min": 2011,
        "median": 2040,
        "max": 2041
      },
      "peakRssMb": {
        "min": 429.4,
        "median": 429.5,
        "max": 429.7
      },
      "rssDeltaMb": {
        "min": 397.8,
        "median": 397.9,
        "max": 399.1
      },
      "peakCpuPercent": {
        "min": 125,
        "median": 130,
        "max": 138
      },
      "cpuMsEstimate": {
        "min": 2236,
        "median": 2242,
        "max": 2280
      },
      "harnessHeapDeltaMb": {
        "min": -5.6,
        "median": -5.1,
        "max": 7.3
      },
      "statSampleCount": 241,
      "rssSampleCount": 241,
      "cpuSampleCount": 241,
      "exitCodes": [
        0
      ]
    },
    {
      "id": "compat-report-registry",
      "label": "Compatibility report plus target registry parse",
      "category": "target-registry",
      "command": "/opt/hostedtoolcache/node/22.22.2/x64/bin/node scripts/generate-report.mjs --check",
      "samples": [
        {
          "wallMs": 2114,
          "peakRssMb": 430.5,
          "rssDeltaMb": 400.1,
          "peakCpuPercent": 125,
          "cpuMsEstimate": 2321,
          "harnessHeapDeltaMb": 7,
          "statSampleCount": 84,
          "rssSampleCount": 84,
          "cpuSampleCount": 84,
          "exitCode": 0,
          "stdoutPreview": "crabpot report check: pass; 0 breakages, 170 warnings, 158 suggestions, 328 issues\nreport targets: /home/runner/work/crabpot/crabpot/reports/crabpot-report.md, /home/runner/work/crabpot/crabpot/reports/crabpot-report.json, /home/runner/work/crabpot/crabpot/reports/crabpot-issues.md",
          "stderrPreview": ""
        },
        {
          "wallMs": 2116,
          "peakRssMb": 431.1,
          "rssDeltaMb": 400.2,
          "peakCpuPercent": 117,
          "cpuMsEstimate": 2285,
          "harnessHeapDeltaMb": -5.5,
          "statSampleCount": 84,
          "rssSampleCount": 84,
          "cpuSampleCount": 84,
          "exitCode": 0,
          "stdoutPreview": "crabpot report check: pass; 0 breakages, 170 warnings, 158 suggestions, 328 issues\nreport targets: /home/runner/work/crabpot/crabpot/reports/crabpot-report.md, /home/runner/work/crabpot/crabpot/reports/crabpot-report.json, /home/runner/work/crabpot/crabpot/reports/crabpot-issues.md",
          "stderrPreview": ""
        },
        {
          "wallMs": 2114,
          "peakRssMb": 430.4,
          "rssDeltaMb": 399.3,
          "peakCpuPercent": 127,
          "cpuMsEstimate": 2321,
          "harnessHeapDeltaMb": 6.9,
          "statSampleCount": 83,
          "rssSampleCount": 83,
          "cpuSampleCount": 83,
          "exitCode": 0,
          "stdoutPreview": "crabpot report check: pass; 0 breakages, 170 warnings, 158 suggestions, 328 issues\nreport targets: /home/runner/work/crabpot/crabpot/reports/crabpot-report.md, /home/runner/work/crabpot/crabpot/reports/crabpot-report.json, /home/runner/work/crabpot/crabpot/reports/crabpot-issues.md",
          "stderrPreview": ""
        }
      ],
      "wallMs": {
        "min": 2114,
        "median": 2114,
        "max": 2116
      },
      "peakRssMb": {
        "min": 430.4,
        "median": 430.5,
        "max": 431.1
      },
      "rssDeltaMb": {
        "min": 399.3,
        "median": 400.1,
        "max": 400.2
      },
      "peakCpuPercent": {
        "min": 117,
        "median": 125,
        "max": 127
      },
      "cpuMsEstimate": {
        "min": 2285,
        "median": 2321,
        "max": 2321
      },
      "harnessHeapDeltaMb": {
        "min": -5.5,
        "median": 6.9,
        "max": 7
      },
      "statSampleCount": 251,
      "rssSampleCount": 251,
      "cpuSampleCount": 251,
      "exitCodes": [
        0
      ]
    },
    {
      "id": "contract-capture",
      "label": "Contract capture inventory",
      "category": "contract-capture",
      "command": "/opt/hostedtoolcache/node/22.22.2/x64/bin/node scripts/capture-contracts.mjs --check",
      "samples": [
        {
          "wallMs": 2228,
          "peakRssMb": 430.7,
          "rssDeltaMb": 399.7,
          "peakCpuPercent": 121,
          "cpuMsEstimate": 2433,
          "harnessHeapDeltaMb": -4.9,
          "statSampleCount": 88,
          "rssSampleCount": 88,
          "cpuSampleCount": 88,
          "exitCode": 0,
          "stdoutPreview": "contract capture: 316 registrations, 95 hooks, 1728 sdk imports, 322 issue probes",
          "stderrPreview": ""
        },
        {
          "wallMs": 2137,
          "peakRssMb": 431.3,
          "rssDeltaMb": 399.5,
          "peakCpuPercent": 119,
          "cpuMsEstimate": 2317,
          "harnessHeapDeltaMb": 6.9,
          "statSampleCount": 85,
          "rssSampleCount": 85,
          "cpuSampleCount": 85,
          "exitCode": 0,
          "stdoutPreview": "contract capture: 316 registrations, 95 hooks, 1728 sdk imports, 322 issue probes",
          "stderrPreview": ""
        },
        {
          "wallMs": 2121,
          "peakRssMb": 430.7,
          "rssDeltaMb": 399.6,
          "peakCpuPercent": 125,
          "cpuMsEstimate": 2308,
          "harnessHeapDeltaMb": -5.2,
          "statSampleCount": 84,
          "rssSampleCount": 84,
          "cpuSampleCount": 84,
          "exitCode": 0,
          "stdoutPreview": "contract capture: 316 registrations, 95 hooks, 1728 sdk imports, 322 issue probes",
          "stderrPreview": ""
        }
      ],
      "wallMs": {
        "min": 2121,
        "median": 2137,
        "max": 2228
      },
      "peakRssMb": {
        "min": 430.7,
        "median": 430.7,
        "max": 431.3
      },
      "rssDeltaMb": {
        "min": 399.5,
        "median": 399.6,
        "max": 399.7
      },
      "peakCpuPercent": {
        "min": 119,
        "median": 121,
        "max": 125
      },
      "cpuMsEstimate": {
        "min": 2308,
        "median": 2317,
        "max": 2433
      },
      "harnessHeapDeltaMb": {
        "min": -5.2,
        "median": -4.9,
        "max": 6.9
      },
      "statSampleCount": 257,
      "rssSampleCount": 257,
      "cpuSampleCount": 257,
      "exitCodes": [
        0
      ]
    },
    {
      "id": "synthetic-probe-plan",
      "label": "Synthetic probe plan",
      "category": "synthetic-probes",
      "command": "/opt/hostedtoolcache/node/22.22.2/x64/bin/node scripts/synthetic-probes.mjs --check",
      "samples": [
        {
          "wallMs": 2153,
          "peakRssMb": 431.7,
          "rssDeltaMb": 401.3,
          "peakCpuPercent": 123,
          "cpuMsEstimate": 2340,
          "harnessHeapDeltaMb": -676.1,
          "statSampleCount": 81,
          "rssSampleCount": 81,
          "cpuSampleCount": 81,
          "exitCode": 0,
          "stdoutPreview": "synthetic probes: 411 ready, 0 blocked, 411 total",
          "stderrPreview": ""
        },
        {
          "wallMs": 2107,
          "peakRssMb": 431.4,
          "rssDeltaMb": 400.2,
          "peakCpuPercent": 122,
          "cpuMsEstimate": 2276,
          "harnessHeapDeltaMb": 0,
          "statSampleCount": 84,
          "rssSampleCount": 84,
          "cpuSampleCount": 84,
          "exitCode": 0,
          "stdoutPreview": "synthetic probes: 411 ready, 0 blocked, 411 total",
          "stderrPreview": ""
        },
        {
          "wallMs": 2117,
          "peakRssMb": 430.8,
          "rssDeltaMb": 402.1,
          "peakCpuPercent": 116,
          "cpuMsEstimate": 2282,
          "harnessHeapDeltaMb": 0.6,
          "statSampleCount": 84,
          "rssSampleCount": 84,
          "cpuSampleCount": 84,
          "exitCode": 0,
          "stdoutPreview": "synthetic probes: 411 ready, 0 blocked, 411 total",
          "stderrPreview": ""
        }
      ],
      "wallMs": {
        "min": 2107,
        "median": 2117,
        "max": 2153
      },
      "peakRssMb": {
        "min": 430.8,
        "median": 431.4,
        "max": 431.7
      },
      "rssDeltaMb": {
        "min": 400.2,
        "median": 401.3,
        "max": 402.1
      },
      "peakCpuPercent": {
        "min": 116,
        "median": 122,
        "max": 123
      },
      "cpuMsEstimate": {
        "min": 2276,
        "median": 2282,
        "max": 2340
      },
      "harnessHeapDeltaMb": {
        "min": -676.1,
        "median": 0,
        "max": 0.6
      },
      "statSampleCount": 249,
      "rssSampleCount": 249,
      "cpuSampleCount": 249,
      "exitCodes": [
        0
      ]
    },
    {
      "id": "cold-import-readiness",
      "label": "Cold import readiness",
      "category": "cold-import",
      "command": "/opt/hostedtoolcache/node/22.22.2/x64/bin/node scripts/cold-import-readiness.mjs --check",
      "samples": [
        {
          "wallMs": 2133,
          "peakRssMb": 434,
          "rssDeltaMb": 404.2,
          "peakCpuPercent": 140,
          "cpuMsEstimate": 2393,
          "harnessHeapDeltaMb": 0.6,
          "statSampleCount": 85,
          "rssSampleCount": 85,
          "cpuSampleCount": 85,
          "exitCode": 0,
          "stdoutPreview": "cold import readiness: 101 entrypoints, 6 ready, 95 blocked",
          "stderrPreview": ""
        },
        {
          "wallMs": 2118,
          "peakRssMb": 437.5,
          "rssDeltaMb": 407.9,
          "peakCpuPercent": 130,
          "cpuMsEstimate": 2328,
          "harnessHeapDeltaMb": -0.8,
          "statSampleCount": 84,
          "rssSampleCount": 84,
          "cpuSampleCount": 84,
          "exitCode": 0,
          "stdoutPreview": "cold import readiness: 101 entrypoints, 6 ready, 95 blocked",
          "stderrPreview": ""
        },
        {
          "wallMs": 2112,
          "peakRssMb": 430.6,
          "rssDeltaMb": 401.8,
          "peakCpuPercent": 130,
          "cpuMsEstimate": 2296,
          "harnessHeapDeltaMb": 0.6,
          "statSampleCount": 84,
          "rssSampleCount": 84,
          "cpuSampleCount": 84,
          "exitCode": 0,
          "stdoutPreview": "cold import readiness: 101 entrypoints, 6 ready, 95 blocked",
          "stderrPreview": ""
        }
      ],
      "wallMs": {
        "min": 2112,
        "median": 2118,
        "max": 2133
      },
      "peakRssMb": {
        "min": 430.6,
        "median": 434,
        "max": 437.5
      },
      "rssDeltaMb": {
        "min": 401.8,
        "median": 404.2,
        "max": 407.9
      },
      "peakCpuPercent": {
        "min": 130,
        "median": 130,
        "max": 140
      },
      "cpuMsEstimate": {
        "min": 2296,
        "median": 2328,
        "max": 2393
      },
      "harnessHeapDeltaMb": {
        "min": -0.8,
        "median": 0.6,
        "max": 0.6
      },
      "statSampleCount": 253,
      "rssSampleCount": 253,
      "cpuSampleCount": 253,
      "exitCodes": [
        0
      ]
    },
    {
      "id": "workspace-plan",
      "label": "Workspace execution plan",
      "category": "workspace-plan",
      "command": "/opt/hostedtoolcache/node/22.22.2/x64/bin/node scripts/workspace-plan.mjs --check",
      "samples": [
        {
          "wallMs": 2164,
          "peakRssMb": 438.1,
          "rssDeltaMb": 408.5,
          "peakCpuPercent": 123,
          "cpuMsEstimate": 2378,
          "harnessHeapDeltaMb": 0.9,
          "statSampleCount": 86,
          "rssSampleCount": 86,
          "cpuSampleCount": 86,
          "exitCode": 0,
          "stdoutPreview": "workspace plan: 101 entrypoints, 40 installs, 40 audits, 11 builds, 101 captures, 101 synthetic probes, 101 artifact dirs",
          "stderrPreview": ""
        },
        {
          "wallMs": 2138,
          "peakRssMb": 438.5,
          "rssDeltaMb": 409,
          "peakCpuPercent": 130,
          "cpuMsEstimate": 2373,
          "harnessHeapDeltaMb": -0.7,
          "statSampleCount": 85,
          "rssSampleCount": 85,
          "cpuSampleCount": 85,
          "exitCode": 0,
          "stdoutPreview": "workspace plan: 101 entrypoints, 40 installs, 40 audits, 11 builds, 101 captures, 101 synthetic probes, 101 artifact dirs",
          "stderrPreview": ""
        },
        {
          "wallMs": 2179,
          "peakRssMb": 439.4,
          "rssDeltaMb": 410.6,
          "peakCpuPercent": 125,
          "cpuMsEstimate": 2388,
          "harnessHeapDeltaMb": 2.4,
          "statSampleCount": 87,
          "rssSampleCount": 87,
          "cpuSampleCount": 87,
          "exitCode": 0,
          "stdoutPreview": "workspace plan: 101 entrypoints, 40 installs, 40 audits, 11 builds, 101 captures, 101 synthetic probes, 101 artifact dirs",
          "stderrPreview": ""
        }
      ],
      "wallMs": {
        "min": 2138,
        "median": 2164,
        "max": 2179
      },
      "peakRssMb": {
        "min": 438.1,
        "median": 438.5,
        "max": 439.4
      },
      "rssDeltaMb": {
        "min": 408.5,
        "median": 409,
        "max": 410.6
      },
      "peakCpuPercent": {
        "min": 123,
        "median": 125,
        "max": 130
      },
      "cpuMsEstimate": {
        "min": 2373,
        "median": 2378,
        "max": 2388
      },
      "harnessHeapDeltaMb": {
        "min": -0.7,
        "median": 0.9,
        "max": 2.4
      },
      "statSampleCount": 258,
      "rssSampleCount": 258,
      "cpuSampleCount": 258,
      "exitCodes": [
        0
      ]
    },
    {
      "id": "platform-probes",
      "label": "Platform and loader probes",
      "category": "platform-probes",
      "command": "/opt/hostedtoolcache/node/22.22.2/x64/bin/node scripts/platform-probes.mjs --check",
      "samples": [
        {
          "wallMs": 2177,
          "peakRssMb": 438,
          "rssDeltaMb": 408.1,
          "peakCpuPercent": 118,
          "cpuMsEstimate": 2345,
          "harnessHeapDeltaMb": -1.9,
          "statSampleCount": 87,
          "rssSampleCount": 87,
          "cpuSampleCount": 87,
          "exitCode": 0,
          "stdoutPreview": "platform probes: 101 entrypoints, 23 TS loader, 14 Windows-risk steps, 14 container-risk steps",
          "stderrPreview": ""
        },
        {
          "wallMs": 2219,
          "peakRssMb": 437.7,
          "rssDeltaMb": 409,
          "peakCpuPercent": 117,
          "cpuMsEstimate": 2399,
          "harnessHeapDeltaMb": 1.1,
          "statSampleCount": 88,
          "rssSampleCount": 88,
          "cpuSampleCount": 88,
          "exitCode": 0,
          "stdoutPreview": "platform probes: 101 entrypoints, 23 TS loader, 14 Windows-risk steps, 14 container-risk steps",
          "stderrPreview": ""
        },
        {
          "wallMs": 2201,
          "peakRssMb": 435.9,
          "rssDeltaMb": 405.7,
          "peakCpuPercent": 133,
          "cpuMsEstimate": 2375,
          "harnessHeapDeltaMb": 1.1,
          "statSampleCount": 87,
          "rssSampleCount": 87,
          "cpuSampleCount": 87,
          "exitCode": 0,
          "stdoutPreview": "platform probes: 101 entrypoints, 23 TS loader, 14 Windows-risk steps, 14 container-risk steps",
          "stderrPreview": ""
        }
      ],
      "wallMs": {
        "min": 2177,
        "median": 2201,
        "max": 2219
      },
      "peakRssMb": {
        "min": 435.9,
        "median": 437.7,
        "max": 438
      },
      "rssDeltaMb": {
        "min": 405.7,
        "median": 408.1,
        "max": 409
      },
      "peakCpuPercent": {
        "min": 117,
        "median": 118,
        "max": 133
      },
      "cpuMsEstimate": {
        "min": 2345,
        "median": 2375,
        "max": 2399
      },
      "harnessHeapDeltaMb": {
        "min": -1.9,
        "median": 1.1,
        "max": 1.1
      },
      "statSampleCount": 262,
      "rssSampleCount": 262,
      "cpuSampleCount": 262,
      "exitCodes": [
        0
      ]
    },
    {
      "id": "import-loop-profile",
      "label": "Repeated cold import capture loop",
      "category": "import-loop",
      "command": "/opt/hostedtoolcache/node/22.22.2/x64/bin/node scripts/import-loop-profile.mjs --check --runs 2",
      "samples": [
        {
          "wallMs": 380,
          "peakRssMb": 60.3,
          "rssDeltaMb": 31.6,
          "peakCpuPercent": 100,
          "cpuMsEstimate": 173,
          "harnessHeapDeltaMb": -1.7,
          "statSampleCount": 15,
          "rssSampleCount": 15,
          "cpuSampleCount": 15,
          "exitCode": 0,
          "stdoutPreview": "import loop profile: 2 runs, p50 74ms / p95 75ms / plugin delta RSS 0.1MB / plugin delta CPU 3ms",
          "stderrPreview": ""
        },
        {
          "wallMs": 376,
          "peakRssMb": 60.4,
          "rssDeltaMb": 31.8,
          "peakCpuPercent": 100,
          "cpuMsEstimate": 164,
          "harnessHeapDeltaMb": 1.3,
          "statSampleCount": 15,
          "rssSampleCount": 15,
          "cpuSampleCount": 15,
          "exitCode": 0,
          "stdoutPreview": "import loop profile: 2 runs, p50 73ms / p95 74ms / plugin delta RSS 0.3MB / plugin delta CPU 9ms",
          "stderrPreview": ""
        },
        {
          "wallMs": 376,
          "peakRssMb": 60.5,
          "rssDeltaMb": 31.8,
          "peakCpuPercent": 100,
          "cpuMsEstimate": 180,
          "harnessHeapDeltaMb": -1.6,
          "statSampleCount": 15,
          "rssSampleCount": 15,
          "cpuSampleCount": 15,
          "exitCode": 0,
          "stdoutPreview": "import loop profile: 2 runs, p50 73ms / p95 74ms / plugin delta RSS 0.4MB / plugin delta CPU 3ms",
          "stderrPreview": ""
        }
      ],
      "wallMs": {
        "min": 376,
        "median": 376,
        "max": 380
      },
      "peakRssMb": {
        "min": 60.3,
        "median": 60.4,
        "max": 60.5
      },
      "rssDeltaMb": {
        "min": 31.6,
        "median": 31.8,
        "max": 31.8
      },
      "peakCpuPercent": {
        "min": 100,
        "median": 100,
        "max": 100
      },
      "cpuMsEstimate": {
        "min": 164,
        "median": 173,
        "max": 180
      },
      "harnessHeapDeltaMb": {
        "min": -1.7,
        "median": -1.6,
        "max": 1.3
      },
      "statSampleCount": 45,
      "rssSampleCount": 45,
      "cpuSampleCount": 45,
      "exitCodes": [
        0
      ]
    }
  ]
}
