{
  "generatedAt": "deterministic",
  "runs": 3,
  "targetOpenClaw": {
    "status": "ok",
    "configuredPath": "./openclaw",
    "compatRecords": 60,
    "hookNames": 35,
    "apiRegistrars": 49,
    "capturedRegistrars": 26,
    "sdkExports": 296,
    "manifestFields": 40,
    "manifestContractFields": 17
  },
  "fixtureInventory": {
    "fixtures": 57,
    "sourceFiles": 1772,
    "observedHooks": 96,
    "observedRegistrations": 193,
    "observedSdkImports": 1157,
    "contractProbes": 323,
    "issueFindings": 329
  },
  "platform": {
    "os": "linux",
    "arch": "x64",
    "node": "v22.22.2",
    "rssSampler": "ps-immediate-25ms",
    "cpuSampler": "ps-percent-immediate-25ms"
  },
  "summary": {
    "commandCount": 9,
    "sampleCount": 27,
    "rssSampleCount": 1477,
    "cpuSampleCount": 1477,
    "wallTimeBasis": "command-median-p95",
    "p50WallMs": 1727,
    "p95WallMs": 1772,
    "maxPeakRssMb": 441.3,
    "maxRssDeltaMb": 412.6,
    "maxCpuMsEstimate": 1933,
    "maxHarnessHeapDeltaMb": 6
  },
  "groups": [
    {
      "category": "baseline",
      "commandCount": 1,
      "p50WallMs": 32,
      "p95WallMs": 33,
      "maxPeakRssMb": 30.8,
      "maxCpuMsEstimate": 0,
      "rssSampleCount": 3,
      "cpuSampleCount": 3,
      "commands": [
        "node-boot"
      ]
    },
    {
      "category": "fixture-scan",
      "commandCount": 1,
      "p50WallMs": 1645,
      "p95WallMs": 1687,
      "maxPeakRssMb": 432,
      "maxCpuMsEstimate": 1817,
      "rssSampleCount": 196,
      "cpuSampleCount": 196,
      "commands": [
        "fixture-inspection"
      ]
    },
    {
      "category": "target-registry",
      "commandCount": 1,
      "p50WallMs": 1710,
      "p95WallMs": 1760,
      "maxPeakRssMb": 433,
      "maxCpuMsEstimate": 1915,
      "rssSampleCount": 205,
      "cpuSampleCount": 205,
      "commands": [
        "compat-report-registry"
      ]
    },
    {
      "category": "contract-capture",
      "commandCount": 1,
      "p50WallMs": 1739,
      "p95WallMs": 1741,
      "maxPeakRssMb": 432.6,
      "maxCpuMsEstimate": 1887,
      "rssSampleCount": 207,
      "cpuSampleCount": 207,
      "commands": [
        "contract-capture"
      ]
    },
    {
      "category": "synthetic-probes",
      "commandCount": 1,
      "p50WallMs": 1727,
      "p95WallMs": 1743,
      "maxPeakRssMb": 432.7,
      "maxCpuMsEstimate": 1877,
      "rssSampleCount": 205,
      "cpuSampleCount": 205,
      "commands": [
        "synthetic-probe-plan"
      ]
    },
    {
      "category": "cold-import",
      "commandCount": 1,
      "p50WallMs": 1735,
      "p95WallMs": 1742,
      "maxPeakRssMb": 432.9,
      "maxCpuMsEstimate": 1907,
      "rssSampleCount": 203,
      "cpuSampleCount": 203,
      "commands": [
        "cold-import-readiness"
      ]
    },
    {
      "category": "workspace-plan",
      "commandCount": 1,
      "p50WallMs": 1751,
      "p95WallMs": 1751,
      "maxPeakRssMb": 441.3,
      "maxCpuMsEstimate": 1933,
      "rssSampleCount": 208,
      "cpuSampleCount": 208,
      "commands": [
        "workspace-plan"
      ]
    },
    {
      "category": "platform-probes",
      "commandCount": 1,
      "p50WallMs": 1772,
      "p95WallMs": 1776,
      "maxPeakRssMb": 439.9,
      "maxCpuMsEstimate": 1920,
      "rssSampleCount": 211,
      "cpuSampleCount": 211,
      "commands": [
        "platform-probes"
      ]
    },
    {
      "category": "import-loop",
      "commandCount": 1,
      "p50WallMs": 325,
      "p95WallMs": 326,
      "maxPeakRssMb": 60.5,
      "maxCpuMsEstimate": 137,
      "rssSampleCount": 39,
      "cpuSampleCount": 39,
      "commands": [
        "import-loop-profile"
      ]
    }
  ],
  "commands": [
    {
      "id": "node-boot",
      "label": "Node boot",
      "category": "baseline",
      "command": "/opt/hostedtoolcache/node/22.22.2/x64/bin/node -e 0",
      "samples": [
        {
          "wallMs": 33,
          "peakRssMb": 30.8,
          "rssDeltaMb": 0,
          "peakCpuPercent": 0,
          "cpuMsEstimate": 0,
          "harnessHeapDeltaMb": 0.3,
          "statSampleCount": 1,
          "rssSampleCount": 1,
          "cpuSampleCount": 1,
          "exitCode": 0,
          "stdoutPreview": "",
          "stderrPreview": ""
        },
        {
          "wallMs": 32,
          "peakRssMb": 28.8,
          "rssDeltaMb": 0,
          "peakCpuPercent": 0,
          "cpuMsEstimate": 0,
          "harnessHeapDeltaMb": 0.3,
          "statSampleCount": 1,
          "rssSampleCount": 1,
          "cpuSampleCount": 1,
          "exitCode": 0,
          "stdoutPreview": "",
          "stderrPreview": ""
        },
        {
          "wallMs": 31,
          "peakRssMb": 28.8,
          "rssDeltaMb": 0,
          "peakCpuPercent": 0,
          "cpuMsEstimate": 0,
          "harnessHeapDeltaMb": 0.3,
          "statSampleCount": 1,
          "rssSampleCount": 1,
          "cpuSampleCount": 1,
          "exitCode": 0,
          "stdoutPreview": "",
          "stderrPreview": ""
        }
      ],
      "wallMs": {
        "min": 31,
        "median": 32,
        "max": 33
      },
      "peakRssMb": {
        "min": 28.8,
        "median": 28.8,
        "max": 30.8
      },
      "rssDeltaMb": {
        "min": 0,
        "median": 0,
        "max": 0
      },
      "peakCpuPercent": {
        "min": 0,
        "median": 0,
        "max": 0
      },
      "cpuMsEstimate": {
        "min": 0,
        "median": 0,
        "max": 0
      },
      "harnessHeapDeltaMb": {
        "min": 0.3,
        "median": 0.3,
        "max": 0.3
      },
      "statSampleCount": 3,
      "rssSampleCount": 3,
      "cpuSampleCount": 3,
      "exitCodes": [
        0
      ]
    },
    {
      "id": "fixture-inspection",
      "label": "Fixture inspection",
      "category": "fixture-scan",
      "command": "/opt/hostedtoolcache/node/22.22.2/x64/bin/node scripts/inspect-fixtures.mjs --check",
      "samples": [
        {
          "wallMs": 1645,
          "peakRssMb": 430.9,
          "rssDeltaMb": 401.1,
          "peakCpuPercent": 130,
          "cpuMsEstimate": 1785,
          "harnessHeapDeltaMb": 6,
          "statSampleCount": 65,
          "rssSampleCount": 65,
          "cpuSampleCount": 65,
          "exitCode": 0,
          "stdoutPreview": "│ 56      │ 'inworld-tts'            │ 'ok'   │ ''                                                                                                                                                                                                                                                                                                                                                                                                                                                                                                                                                                                                          │ 'definePluginEntry,registerSpeechProvider'                                                                                                                                                                                                                                                                                                                                                                                                                                                                                                                                                                                                                                                                                                                                                                                                                                                                                                                                                                                                                                                                                                                                                                                                                                          │ 'speechProviders'                                                                                                                                                                                                                                                                                                                                                                        │\n└─────────┴──────────────────────────┴────────┴─────────────────────────────────────────────────────────────────────────────────────────────────────────────────────────────────────────────────────────────────────────────────────────────────────────────────────────────────────────────────────────────────────────────────────────────────────────────────────────────────────────────────────────────────────────────────────────────────────────────────────────────────────────────────────────────────────────────────────────────────────────────────────────────────────────────────────────────────────────────────────────────────────────────┴─────────────────────────────────────────────────────────────────────────────────────────────────────────────────────────────────────────────────────────────────────────────────────────────────────────────────────────────────────────────────────────────────────────────────────────────────────────────────────────────────────────────────────────────────────────────────────────────────────────────────────────────────────────────────────────────────────────────────────────────────────────────────────────────────────────────────────────────────────────────────────────────────────────────────────────────────────────────────────────────────────────────────────────────────────────────────────────────────────────────────────────────────────────────────────────────────────────────────────────────────────────────────────────────────────────────────────────────────────────────────────────────────────────────────────────────────────────────────────────────────────────────────────────────────────────────────────────────────────────────────────────────────────────────────────────────────────────────────────────────────────────────────────────────────────────────────────────────────────────────────────────────────────────────────────┴──────────────────────────────────────────────────────────────────────────────────────────────────────────────────────────────────────────────────────────────────────────────────────────────────────────────────────────────────────────────────────────────────────────────────────────────────────────────────────────────────────────────────────────────────────────────────────────┘",
          "stderrPreview": ""
        },
        {
          "wallMs": 1687,
          "peakRssMb": 432,
          "rssDeltaMb": 402.9,
          "peakCpuPercent": 128,
          "cpuMsEstimate": 1817,
          "harnessHeapDeltaMb": -6.5,
          "statSampleCount": 66,
          "rssSampleCount": 66,
          "cpuSampleCount": 66,
          "exitCode": 0,
          "stdoutPreview": "│ 56      │ 'inworld-tts'            │ 'ok'   │ ''                                                                                                                                                                                                                                                                                                                                                                                                                                                                                                                                                                                                          │ 'definePluginEntry,registerSpeechProvider'                                                                                                                                                                                                                                                                                                                                                                                                                                                                                                                                                                                                                                                                                                                                                                                                                                                                                                                                                                                                                                                                                                                                                                                                                                          │ 'speechProviders'                                                                                                                                                                                                                                                                                                                                                                        │\n└─────────┴──────────────────────────┴────────┴─────────────────────────────────────────────────────────────────────────────────────────────────────────────────────────────────────────────────────────────────────────────────────────────────────────────────────────────────────────────────────────────────────────────────────────────────────────────────────────────────────────────────────────────────────────────────────────────────────────────────────────────────────────────────────────────────────────────────────────────────────────────────────────────────────────────────────────────────────────────────────────────────────────────┴─────────────────────────────────────────────────────────────────────────────────────────────────────────────────────────────────────────────────────────────────────────────────────────────────────────────────────────────────────────────────────────────────────────────────────────────────────────────────────────────────────────────────────────────────────────────────────────────────────────────────────────────────────────────────────────────────────────────────────────────────────────────────────────────────────────────────────────────────────────────────────────────────────────────────────────────────────────────────────────────────────────────────────────────────────────────────────────────────────────────────────────────────────────────────────────────────────────────────────────────────────────────────────────────────────────────────────────────────────────────────────────────────────────────────────────────────────────────────────────────────────────────────────────────────────────────────────────────────────────────────────────────────────────────────────────────────────────────────────────────────────────────────────────────────────────────────────────────────────────────────────────────────────────────────────┴──────────────────────────────────────────────────────────────────────────────────────────────────────────────────────────────────────────────────────────────────────────────────────────────────────────────────────────────────────────────────────────────────────────────────────────────────────────────────────────────────────────────────────────────────────────────────────────┘",
          "stderrPreview": ""
        },
        {
          "wallMs": 1640,
          "peakRssMb": 430.3,
          "rssDeltaMb": 399.3,
          "peakCpuPercent": 142,
          "cpuMsEstimate": 1815,
          "harnessHeapDeltaMb": 5.9,
          "statSampleCount": 65,
          "rssSampleCount": 65,
          "cpuSampleCount": 65,
          "exitCode": 0,
          "stdoutPreview": "│ 56      │ 'inworld-tts'            │ 'ok'   │ ''                                                                                                                                                                                                                                                                                                                                                                                                                                                                                                                                                                                                          │ 'definePluginEntry,registerSpeechProvider'                                                                                                                                                                                                                                                                                                                                                                                                                                                                                                                                                                                                                                                                                                                                                                                                                                                                                                                                                                                                                                                                                                                                                                                                                                          │ 'speechProviders'                                                                                                                                                                                                                                                                                                                                                                        │\n└─────────┴──────────────────────────┴────────┴─────────────────────────────────────────────────────────────────────────────────────────────────────────────────────────────────────────────────────────────────────────────────────────────────────────────────────────────────────────────────────────────────────────────────────────────────────────────────────────────────────────────────────────────────────────────────────────────────────────────────────────────────────────────────────────────────────────────────────────────────────────────────────────────────────────────────────────────────────────────────────────────────────────────┴─────────────────────────────────────────────────────────────────────────────────────────────────────────────────────────────────────────────────────────────────────────────────────────────────────────────────────────────────────────────────────────────────────────────────────────────────────────────────────────────────────────────────────────────────────────────────────────────────────────────────────────────────────────────────────────────────────────────────────────────────────────────────────────────────────────────────────────────────────────────────────────────────────────────────────────────────────────────────────────────────────────────────────────────────────────────────────────────────────────────────────────────────────────────────────────────────────────────────────────────────────────────────────────────────────────────────────────────────────────────────────────────────────────────────────────────────────────────────────────────────────────────────────────────────────────────────────────────────────────────────────────────────────────────────────────────────────────────────────────────────────────────────────────────────────────────────────────────────────────────────────────────────────────────────────┴──────────────────────────────────────────────────────────────────────────────────────────────────────────────────────────────────────────────────────────────────────────────────────────────────────────────────────────────────────────────────────────────────────────────────────────────────────────────────────────────────────────────────────────────────────────────────────────┘",
          "stderrPreview": ""
        }
      ],
      "wallMs": {
        "min": 1640,
        "median": 1645,
        "max": 1687
      },
      "peakRssMb": {
        "min": 430.3,
        "median": 430.9,
        "max": 432
      },
      "rssDeltaMb": {
        "min": 399.3,
        "median": 401.1,
        "max": 402.9
      },
      "peakCpuPercent": {
        "min": 128,
        "median": 130,
        "max": 142
      },
      "cpuMsEstimate": {
        "min": 1785,
        "median": 1815,
        "max": 1817
      },
      "harnessHeapDeltaMb": {
        "min": -6.5,
        "median": 5.9,
        "max": 6
      },
      "statSampleCount": 196,
      "rssSampleCount": 196,
      "cpuSampleCount": 196,
      "exitCodes": [
        0
      ]
    },
    {
      "id": "compat-report-registry",
      "label": "Compatibility report plus target registry parse",
      "category": "target-registry",
      "command": "/opt/hostedtoolcache/node/22.22.2/x64/bin/node scripts/generate-report.mjs --check",
      "samples": [
        {
          "wallMs": 1702,
          "peakRssMb": 432.8,
          "rssDeltaMb": 404,
          "peakCpuPercent": 133,
          "cpuMsEstimate": 1828,
          "harnessHeapDeltaMb": -6.7,
          "statSampleCount": 67,
          "rssSampleCount": 67,
          "cpuSampleCount": 67,
          "exitCode": 0,
          "stdoutPreview": "crabpot report check: pass; 0 breakages, 171 warnings, 158 suggestions, 329 issues\nreport targets: /home/runner/work/crabpot/crabpot/reports/crabpot-report.md, /home/runner/work/crabpot/crabpot/reports/crabpot-report.json, /home/runner/work/crabpot/crabpot/reports/crabpot-issues.md",
          "stderrPreview": ""
        },
        {
          "wallMs": 1710,
          "peakRssMb": 431.9,
          "rssDeltaMb": 403.2,
          "peakCpuPercent": 116,
          "cpuMsEstimate": 1835,
          "harnessHeapDeltaMb": 5.7,
          "statSampleCount": 68,
          "rssSampleCount": 68,
          "cpuSampleCount": 68,
          "exitCode": 0,
          "stdoutPreview": "crabpot report check: pass; 0 breakages, 171 warnings, 158 suggestions, 329 issues\nreport targets: /home/runner/work/crabpot/crabpot/reports/crabpot-report.md, /home/runner/work/crabpot/crabpot/reports/crabpot-report.json, /home/runner/work/crabpot/crabpot/reports/crabpot-issues.md",
          "stderrPreview": ""
        },
        {
          "wallMs": 1760,
          "peakRssMb": 433,
          "rssDeltaMb": 402.7,
          "peakCpuPercent": 150,
          "cpuMsEstimate": 1915,
          "harnessHeapDeltaMb": -6.3,
          "statSampleCount": 70,
          "rssSampleCount": 70,
          "cpuSampleCount": 70,
          "exitCode": 0,
          "stdoutPreview": "crabpot report check: pass; 0 breakages, 171 warnings, 158 suggestions, 329 issues\nreport targets: /home/runner/work/crabpot/crabpot/reports/crabpot-report.md, /home/runner/work/crabpot/crabpot/reports/crabpot-report.json, /home/runner/work/crabpot/crabpot/reports/crabpot-issues.md",
          "stderrPreview": ""
        }
      ],
      "wallMs": {
        "min": 1702,
        "median": 1710,
        "max": 1760
      },
      "peakRssMb": {
        "min": 431.9,
        "median": 432.8,
        "max": 433
      },
      "rssDeltaMb": {
        "min": 402.7,
        "median": 403.2,
        "max": 404
      },
      "peakCpuPercent": {
        "min": 116,
        "median": 133,
        "max": 150
      },
      "cpuMsEstimate": {
        "min": 1828,
        "median": 1835,
        "max": 1915
      },
      "harnessHeapDeltaMb": {
        "min": -6.7,
        "median": -6.3,
        "max": 5.7
      },
      "statSampleCount": 205,
      "rssSampleCount": 205,
      "cpuSampleCount": 205,
      "exitCodes": [
        0
      ]
    },
    {
      "id": "contract-capture",
      "label": "Contract capture inventory",
      "category": "contract-capture",
      "command": "/opt/hostedtoolcache/node/22.22.2/x64/bin/node scripts/capture-contracts.mjs --check",
      "samples": [
        {
          "wallMs": 1733,
          "peakRssMb": 432.2,
          "rssDeltaMb": 401.9,
          "peakCpuPercent": 128,
          "cpuMsEstimate": 1865,
          "harnessHeapDeltaMb": 5.7,
          "statSampleCount": 69,
          "rssSampleCount": 69,
          "cpuSampleCount": 69,
          "exitCode": 0,
          "stdoutPreview": "contract capture: 323 registrations, 98 hooks, 2122 sdk imports, 323 issue probes",
          "stderrPreview": ""
        },
        {
          "wallMs": 1741,
          "peakRssMb": 432.6,
          "rssDeltaMb": 403.8,
          "peakCpuPercent": 115,
          "cpuMsEstimate": 1854,
          "harnessHeapDeltaMb": -6.3,
          "statSampleCount": 69,
          "rssSampleCount": 69,
          "cpuSampleCount": 69,
          "exitCode": 0,
          "stdoutPreview": "contract capture: 323 registrations, 98 hooks, 2122 sdk imports, 323 issue probes",
          "stderrPreview": ""
        },
        {
          "wallMs": 1739,
          "peakRssMb": 431.7,
          "rssDeltaMb": 401.1,
          "peakCpuPercent": 144,
          "cpuMsEstimate": 1887,
          "harnessHeapDeltaMb": 5.8,
          "statSampleCount": 69,
          "rssSampleCount": 69,
          "cpuSampleCount": 69,
          "exitCode": 0,
          "stdoutPreview": "contract capture: 323 registrations, 98 hooks, 2122 sdk imports, 323 issue probes",
          "stderrPreview": ""
        }
      ],
      "wallMs": {
        "min": 1733,
        "median": 1739,
        "max": 1741
      },
      "peakRssMb": {
        "min": 431.7,
        "median": 432.2,
        "max": 432.6
      },
      "rssDeltaMb": {
        "min": 401.1,
        "median": 401.9,
        "max": 403.8
      },
      "peakCpuPercent": {
        "min": 115,
        "median": 128,
        "max": 144
      },
      "cpuMsEstimate": {
        "min": 1854,
        "median": 1865,
        "max": 1887
      },
      "harnessHeapDeltaMb": {
        "min": -6.3,
        "median": 5.7,
        "max": 5.8
      },
      "statSampleCount": 207,
      "rssSampleCount": 207,
      "cpuSampleCount": 207,
      "exitCodes": [
        0
      ]
    },
    {
      "id": "synthetic-probe-plan",
      "label": "Synthetic probe plan",
      "category": "synthetic-probes",
      "command": "/opt/hostedtoolcache/node/22.22.2/x64/bin/node scripts/synthetic-probes.mjs --check",
      "samples": [
        {
          "wallMs": 1743,
          "peakRssMb": 432.1,
          "rssDeltaMb": 403.3,
          "peakCpuPercent": 120,
          "cpuMsEstimate": 1846,
          "harnessHeapDeltaMb": -6.4,
          "statSampleCount": 69,
          "rssSampleCount": 69,
          "cpuSampleCount": 69,
          "exitCode": 0,
          "stdoutPreview": "synthetic probes: 421 ready, 0 blocked, 421 total",
          "stderrPreview": ""
        },
        {
          "wallMs": 1727,
          "peakRssMb": 432.7,
          "rssDeltaMb": 402,
          "peakCpuPercent": 117,
          "cpuMsEstimate": 1863,
          "harnessHeapDeltaMb": 5.8,
          "statSampleCount": 68,
          "rssSampleCount": 68,
          "cpuSampleCount": 68,
          "exitCode": 0,
          "stdoutPreview": "synthetic probes: 421 ready, 0 blocked, 421 total",
          "stderrPreview": ""
        },
        {
          "wallMs": 1722,
          "peakRssMb": 432.2,
          "rssDeltaMb": 401.6,
          "peakCpuPercent": 130,
          "cpuMsEstimate": 1877,
          "harnessHeapDeltaMb": -6.4,
          "statSampleCount": 68,
          "rssSampleCount": 68,
          "cpuSampleCount": 68,
          "exitCode": 0,
          "stdoutPreview": "synthetic probes: 421 ready, 0 blocked, 421 total",
          "stderrPreview": ""
        }
      ],
      "wallMs": {
        "min": 1722,
        "median": 1727,
        "max": 1743
      },
      "peakRssMb": {
        "min": 432.1,
        "median": 432.2,
        "max": 432.7
      },
      "rssDeltaMb": {
        "min": 401.6,
        "median": 402,
        "max": 403.3
      },
      "peakCpuPercent": {
        "min": 117,
        "median": 120,
        "max": 130
      },
      "cpuMsEstimate": {
        "min": 1846,
        "median": 1863,
        "max": 1877
      },
      "harnessHeapDeltaMb": {
        "min": -6.4,
        "median": -6.4,
        "max": 5.8
      },
      "statSampleCount": 205,
      "rssSampleCount": 205,
      "cpuSampleCount": 205,
      "exitCodes": [
        0
      ]
    },
    {
      "id": "cold-import-readiness",
      "label": "Cold import readiness",
      "category": "cold-import",
      "command": "/opt/hostedtoolcache/node/22.22.2/x64/bin/node scripts/cold-import-readiness.mjs --check",
      "samples": [
        {
          "wallMs": 1742,
          "peakRssMb": 431.9,
          "rssDeltaMb": 401,
          "peakCpuPercent": 133,
          "cpuMsEstimate": 1907,
          "harnessHeapDeltaMb": -675.7,
          "statSampleCount": 67,
          "rssSampleCount": 67,
          "cpuSampleCount": 67,
          "exitCode": 0,
          "stdoutPreview": "cold import readiness: 103 entrypoints, 6 ready, 97 blocked",
          "stderrPreview": ""
        },
        {
          "wallMs": 1705,
          "peakRssMb": 432.9,
          "rssDeltaMb": 403.2,
          "peakCpuPercent": 130,
          "cpuMsEstimate": 1847,
          "harnessHeapDeltaMb": 0,
          "statSampleCount": 67,
          "rssSampleCount": 67,
          "cpuSampleCount": 67,
          "exitCode": 0,
          "stdoutPreview": "cold import readiness: 103 entrypoints, 6 ready, 97 blocked",
          "stderrPreview": ""
        },
        {
          "wallMs": 1735,
          "peakRssMb": 431.8,
          "rssDeltaMb": 403.1,
          "peakCpuPercent": 123,
          "cpuMsEstimate": 1872,
          "harnessHeapDeltaMb": 0.1,
          "statSampleCount": 69,
          "rssSampleCount": 69,
          "cpuSampleCount": 69,
          "exitCode": 0,
          "stdoutPreview": "cold import readiness: 103 entrypoints, 6 ready, 97 blocked",
          "stderrPreview": ""
        }
      ],
      "wallMs": {
        "min": 1705,
        "median": 1735,
        "max": 1742
      },
      "peakRssMb": {
        "min": 431.8,
        "median": 431.9,
        "max": 432.9
      },
      "rssDeltaMb": {
        "min": 401,
        "median": 403.1,
        "max": 403.2
      },
      "peakCpuPercent": {
        "min": 123,
        "median": 130,
        "max": 133
      },
      "cpuMsEstimate": {
        "min": 1847,
        "median": 1872,
        "max": 1907
      },
      "harnessHeapDeltaMb": {
        "min": -675.7,
        "median": 0,
        "max": 0.1
      },
      "statSampleCount": 203,
      "rssSampleCount": 203,
      "cpuSampleCount": 203,
      "exitCodes": [
        0
      ]
    },
    {
      "id": "workspace-plan",
      "label": "Workspace execution plan",
      "category": "workspace-plan",
      "command": "/opt/hostedtoolcache/node/22.22.2/x64/bin/node scripts/workspace-plan.mjs --check",
      "samples": [
        {
          "wallMs": 1747,
          "peakRssMb": 441.3,
          "rssDeltaMb": 412.6,
          "peakCpuPercent": 140,
          "cpuMsEstimate": 1904,
          "harnessHeapDeltaMb": -0.5,
          "statSampleCount": 69,
          "rssSampleCount": 69,
          "cpuSampleCount": 69,
          "exitCode": 0,
          "stdoutPreview": "workspace plan: 103 entrypoints, 43 installs, 43 audits, 11 builds, 103 captures, 103 synthetic probes, 103 artifact dirs",
          "stderrPreview": ""
        },
        {
          "wallMs": 1751,
          "peakRssMb": 439.5,
          "rssDeltaMb": 410.7,
          "peakCpuPercent": 140,
          "cpuMsEstimate": 1910,
          "harnessHeapDeltaMb": 1.2,
          "statSampleCount": 69,
          "rssSampleCount": 69,
          "cpuSampleCount": 69,
          "exitCode": 0,
          "stdoutPreview": "workspace plan: 103 entrypoints, 43 installs, 43 audits, 11 builds, 103 captures, 103 synthetic probes, 103 artifact dirs",
          "stderrPreview": ""
        },
        {
          "wallMs": 1751,
          "peakRssMb": 434.7,
          "rssDeltaMb": 405.9,
          "peakCpuPercent": 140,
          "cpuMsEstimate": 1933,
          "harnessHeapDeltaMb": -0.1,
          "statSampleCount": 70,
          "rssSampleCount": 70,
          "cpuSampleCount": 70,
          "exitCode": 0,
          "stdoutPreview": "workspace plan: 103 entrypoints, 43 installs, 43 audits, 11 builds, 103 captures, 103 synthetic probes, 103 artifact dirs",
          "stderrPreview": ""
        }
      ],
      "wallMs": {
        "min": 1747,
        "median": 1751,
        "max": 1751
      },
      "peakRssMb": {
        "min": 434.7,
        "median": 439.5,
        "max": 441.3
      },
      "rssDeltaMb": {
        "min": 405.9,
        "median": 410.7,
        "max": 412.6
      },
      "peakCpuPercent": {
        "min": 140,
        "median": 140,
        "max": 140
      },
      "cpuMsEstimate": {
        "min": 1904,
        "median": 1910,
        "max": 1933
      },
      "harnessHeapDeltaMb": {
        "min": -0.5,
        "median": -0.1,
        "max": 1.2
      },
      "statSampleCount": 208,
      "rssSampleCount": 208,
      "cpuSampleCount": 208,
      "exitCodes": [
        0
      ]
    },
    {
      "id": "platform-probes",
      "label": "Platform and loader probes",
      "category": "platform-probes",
      "command": "/opt/hostedtoolcache/node/22.22.2/x64/bin/node scripts/platform-probes.mjs --check",
      "samples": [
        {
          "wallMs": 1754,
          "peakRssMb": 439.9,
          "rssDeltaMb": 411.2,
          "peakCpuPercent": 120,
          "cpuMsEstimate": 1893,
          "harnessHeapDeltaMb": -0.2,
          "statSampleCount": 70,
          "rssSampleCount": 70,
          "cpuSampleCount": 70,
          "exitCode": 0,
          "stdoutPreview": "platform probes: 103 entrypoints, 25 TS loader, 14 Windows-risk steps, 14 container-risk steps",
          "stderrPreview": ""
        },
        {
          "wallMs": 1772,
          "peakRssMb": 439.5,
          "rssDeltaMb": 410.7,
          "peakCpuPercent": 119,
          "cpuMsEstimate": 1877,
          "harnessHeapDeltaMb": -0.1,
          "statSampleCount": 70,
          "rssSampleCount": 70,
          "cpuSampleCount": 70,
          "exitCode": 0,
          "stdoutPreview": "platform probes: 103 entrypoints, 25 TS loader, 14 Windows-risk steps, 14 container-risk steps",
          "stderrPreview": ""
        },
        {
          "wallMs": 1776,
          "peakRssMb": 436.2,
          "rssDeltaMb": 406.5,
          "peakCpuPercent": 130,
          "cpuMsEstimate": 1920,
          "harnessHeapDeltaMb": 0,
          "statSampleCount": 71,
          "rssSampleCount": 71,
          "cpuSampleCount": 71,
          "exitCode": 0,
          "stdoutPreview": "platform probes: 103 entrypoints, 25 TS loader, 14 Windows-risk steps, 14 container-risk steps",
          "stderrPreview": ""
        }
      ],
      "wallMs": {
        "min": 1754,
        "median": 1772,
        "max": 1776
      },
      "peakRssMb": {
        "min": 436.2,
        "median": 439.5,
        "max": 439.9
      },
      "rssDeltaMb": {
        "min": 406.5,
        "median": 410.7,
        "max": 411.2
      },
      "peakCpuPercent": {
        "min": 119,
        "median": 120,
        "max": 130
      },
      "cpuMsEstimate": {
        "min": 1877,
        "median": 1893,
        "max": 1920
      },
      "harnessHeapDeltaMb": {
        "min": -0.2,
        "median": -0.1,
        "max": 0
      },
      "statSampleCount": 211,
      "rssSampleCount": 211,
      "cpuSampleCount": 211,
      "exitCodes": [
        0
      ]
    },
    {
      "id": "import-loop-profile",
      "label": "Repeated cold import capture loop",
      "category": "import-loop",
      "command": "/opt/hostedtoolcache/node/22.22.2/x64/bin/node scripts/import-loop-profile.mjs --check --runs 2",
      "samples": [
        {
          "wallMs": 325,
          "peakRssMb": 60.5,
          "rssDeltaMb": 31.7,
          "peakCpuPercent": 100,
          "cpuMsEstimate": 137,
          "harnessHeapDeltaMb": 1.2,
          "statSampleCount": 13,
          "rssSampleCount": 13,
          "cpuSampleCount": 13,
          "exitCode": 0,
          "stdoutPreview": "import loop profile: 2 runs, p50 64ms / p95 65ms / plugin delta RSS 0.2MB / plugin delta CPU 11ms",
          "stderrPreview": ""
        },
        {
          "wallMs": 326,
          "peakRssMb": 60.5,
          "rssDeltaMb": 31.7,
          "peakCpuPercent": 100,
          "cpuMsEstimate": 136,
          "harnessHeapDeltaMb": -0.3,
          "statSampleCount": 13,
          "rssSampleCount": 13,
          "cpuSampleCount": 13,
          "exitCode": 0,
          "stdoutPreview": "import loop profile: 2 runs, p50 65ms / p95 65ms / plugin delta RSS 1MB / plugin delta CPU 0ms",
          "stderrPreview": ""
        },
        {
          "wallMs": 325,
          "peakRssMb": 60.5,
          "rssDeltaMb": 31.7,
          "peakCpuPercent": 100,
          "cpuMsEstimate": 137,
          "harnessHeapDeltaMb": 1.2,
          "statSampleCount": 13,
          "rssSampleCount": 13,
          "cpuSampleCount": 13,
          "exitCode": 0,
          "stdoutPreview": "import loop profile: 2 runs, p50 65ms / p95 65ms / plugin delta RSS 0MB / plugin delta CPU 0ms",
          "stderrPreview": ""
        }
      ],
      "wallMs": {
        "min": 325,
        "median": 325,
        "max": 326
      },
      "peakRssMb": {
        "min": 60.5,
        "median": 60.5,
        "max": 60.5
      },
      "rssDeltaMb": {
        "min": 31.7,
        "median": 31.7,
        "max": 31.7
      },
      "peakCpuPercent": {
        "min": 100,
        "median": 100,
        "max": 100
      },
      "cpuMsEstimate": {
        "min": 136,
        "median": 137,
        "max": 137
      },
      "harnessHeapDeltaMb": {
        "min": -0.3,
        "median": 1.2,
        "max": 1.2
      },
      "statSampleCount": 39,
      "rssSampleCount": 39,
      "cpuSampleCount": 39,
      "exitCodes": [
        0
      ]
    }
  ]
}
